setup.py
src/nous/__init__.py
src/nous.testbrowser.egg-info/PKG-INFO
src/nous.testbrowser.egg-info/SOURCES.txt
src/nous.testbrowser.egg-info/dependency_links.txt
src/nous.testbrowser.egg-info/namespace_packages.txt
src/nous.testbrowser.egg-info/not-zip-safe
src/nous.testbrowser.egg-info/requires.txt
src/nous.testbrowser.egg-info/top_level.txt
src/nous/testbrowser/__init__.py