Metadata-Version: 1.0
Name: nous.testbrowser
Version: 0.1.0
Summary: Nous testbrowser goodies.
Home-page: http://github.com/Ignas/nous.testbrowser/
Author: Ignas Mikalajunas
Author-email: ignas@nous.lt
License: GPL
Platform: UNKNOWN
Classifier: Development Status :: 3 - Alpha
Classifier: Environment :: Web Environment
Classifier: Intended Audience :: Developers
Classifier: License :: OSI Approved :: GNU General Public License (GPL)
Classifier: Programming Language :: Python
